setup.py
artpacker/__init__.py
artpacker/artpacker.py
artpacker/cli.py
artpacker.egg-info/PKG-INFO
artpacker.egg-info/SOURCES.txt
artpacker.egg-info/dependency_links.txt
artpacker.egg-info/requires.txt
artpacker.egg-info/top_level.txt
artpacker/metadata/__init__.py
artpacker/metadata/dummy.py
artpacker/metadata/json.py
artpacker/packer/__init__.py
artpacker/packer/simple.py
artpacker/saver/__init__.py
artpacker/saver/jpeg.py
artpacker/saver/png.py
bin/art-packer