Metadata-Version: 1.0
Name: artpacker
Version: 1.0.1
Summary: Image resources packer to sprite sheets
Home-page: https://github.com/Miroff/art-packer
Author: Maksim Gurtovenko
Author-email: maksim@gurtovenko.name
License: UNKNOWN
Platform: UNKNOWN
